MANIFEST.in
README.md
bfdpie.c
bfdpie_build.sh
requirements.txt
setup.py
bfdpie/__init__.py
bfdpie/bfdpie.py
bfdpie.egg-info/PKG-INFO
bfdpie.egg-info/SOURCES.txt
bfdpie.egg-info/dependency_links.txt
bfdpie.egg-info/requires.txt
bfdpie.egg-info/top_level.txt
bfdpie/bin/dummy.elf