Metadata-Version: 1.1
Name: bfdpie
Version: 0.1.15
Summary: A tiny interface around a subset of libBFD. Code based on https://github.com/Groundworkstech/pybfd
Home-page: https://github.com/malisal/bfdpie
Author: Luka Malisa
Author-email: luka.malisha@gmail.com
License: UNKNOWN
Keywords: binary,libbfd
Platform: any
Classifier: Development Status :: 3 - Alpha
Classifier: Intended Audience :: Developers
Classifier: License :: OSI Approved :: MIT License
Classifier: Programming Language :: Python :: 2
Classifier: Programming Language :: Python :: 3
